AUTHORS
LICENSE
MANIFEST.in
README.rst
setup.py
cms_themes/__init__.py
cms_themes/admin.py
cms_themes/models.py
cms_themes/migrations/0001_initial.py
cms_themes/migrations/0002_auto__add_field_theme_theme_file.py
cms_themes/migrations/__init__.py
demo/__init__.py
demo/manage.py
demo/settings.py
demo/urls.py
demo/cms_themes/__init__.py
demo/cms_themes/admin.py
demo/cms_themes/models.py
demo/cms_themes/migrations/0001_initial.py
demo/cms_themes/migrations/0002_auto__add_field_theme_theme_file.py
demo/cms_themes/migrations/__init__.py
django_cms_themes.egg-info/PKG-INFO
django_cms_themes.egg-info/SOURCES.txt
django_cms_themes.egg-info/dependency_links.txt
django_cms_themes.egg-info/not-zip-safe
django_cms_themes.egg-info/requires.txt
django_cms_themes.egg-info/top_level.txt