Metadata-Version: 1.1
Name: django-cms-themes
Version: 1.0.11
Summary: Load prepackaged themes (templates and accompanying media) into Django CMS projects through the admin
Home-page: http://github.com/megamark16/django-cms-themes
Author: Mark Ransom
Author-email: megamark16@gmail.com
License: BSD
Platform: OS Independent
Classifier: Development Status :: 4 - Beta
Classifier: Framework :: Django
Classifier: Intended Audience :: Developers
Classifier: License :: OSI Approved :: BSD License
Classifier: Operating System :: OS Independent
Classifier: Programming Language :: Python
Classifier: Topic :: Internet :: WWW/HTTP
Classifier: Topic :: Internet :: WWW/HTTP :: Dynamic Content
